flox/__init__.py
flox/cli.py
flox/click.py
flox/config/__init__.py
flox/config/command.py
flox/config/parameters.py
flox/config/remotes.py
flox/config/secrets.py
flox/info/__init__.py
flox/info/command.py
flox/plugins/__init__.py
flox/plugins/command.py
flox/plugins/manager.py
flox/profile/__init__.py
flox/profile/command.py
flox/project/__init__.py
flox/project/command.py
flox/utils/__init__.py
flox/utils/diff.py
flox_cli-0.5.2.dist-info/entry_points.txt
flox_cli-0.5.2.dist-info/LICENSE
flox_cli-0.5.2.dist-info/WHEEL
flox_cli-0.5.2.dist-info/METADATA
flox_cli-0.5.2.dist-info/RECORD
